{
  "resourceType": "Patient",
  "id": "MRN-01136108405",
  "identifier": [
    {
      "use": "usual",
      "type": {
        "coding": [
          {
            "system": "http://terminology.hl7.org/CodeSystem/v2-0203",
            "code": "MR",
            "display": "Medical Record number"
          }
        ]
      },
      "system": "DCM4CHEE.F0D1132A.null",
      "value": "22090620180417"
    }
  ],
  "name": [
    {
      "use": "usual",
      "text": "OB TWIN EARLY 3.0 EPIQ7G",
      "family": "OB TWIN EARLY 3.0",
      "given": [
        "EPIQ7G"
      ]
    }
  ],
  "gender": "female"
}