{
  "resourceType": "Patient",
  "id": "MRN-01112934388",
  "identifier": [
    {
      "use": "usual",
      "type": {
        "coding": [
          {
            "system": "http://terminology.hl7.org/CodeSystem/v2-0203",
            "code": "MR",
            "display": "Medical Record number"
          }
        ]
      },
      "system": "DCM4CHEE.E8E1DC02.null",
      "value": "34139bc5-aa9f-48fc-a5f7-74346e8e4710"
    }
  ],
  "name": [
    {
      "use": "usual",
      "text": "MV_PP1-004",
      "family": "MV_PP1-004"
    }
  ],
  "gender": "unknown"
}