{
  "resourceType": "Patient",
  "id": "MRN-1143083875",
  "identifier": [
    {
      "use": "usual",
      "type": {
        "coding": [
          {
            "system": "http://terminology.hl7.org/CodeSystem/v2-0203",
            "code": "MR",
            "display": "Medical Record number"
          }
        ]
      },
      "system": "DCM4CHEE.1D4C07CC.06CF86CA",
      "value": "456745365"
    },
    {
      "use": "secondary",
      "type": {
        "coding": [
          {
            "system": "http://terminology.hl7.org/CodeSystem/v2-0203",
            "code": "MR",
            "display": "Medical Record number"
          }
        ]
      },
      "value": "56834654"
    }
  ],
  "name": [
    {
      "use": "usual",
      "text": "Vascular Report Verification Fname",
      "family": "Vascular Report Verification",
      "given": [
        "Fname"
      ]
    }
  ],
  "gender": "male",
  "birthDate": "1955-12-12"
}